intmaniac/__init__.py
intmaniac/__main__.py
intmaniac/defaults.py
intmaniac/dockhelpers.py
intmaniac/maniac_file.py
intmaniac/testrun.py
intmaniac/tools.py
intmaniac/version.py
intmaniac/output/__init__.py
intmaniac/output/base.py
intmaniac/output/teamcity.py
intmaniac-0.18.1.dist-info/DESCRIPTION.rst
intmaniac-0.18.1.dist-info/METADATA
intmaniac-0.18.1.dist-info/RECORD
intmaniac-0.18.1.dist-info/WHEEL
intmaniac-0.18.1.dist-info/entry_points.txt
intmaniac-0.18.1.dist-info/metadata.json
intmaniac-0.18.1.dist-info/top_level.txt
tests/__init__.py
tests/configsetup.py
tests/fake_container.py
tests/mocksetup.py
tests/testcomposewrapper.py
tests/testfilehandling.py
tests/testoutput.py
tests/testrun.py
tests/testtools.py
tests/testv3file.py
