Metadata-Version: 2.0
Name: intmaniac
Version: 0.18.1
Summary: A generic integration test tool utilizing docker-compose (for now)
Home-page: https://github.com/flypenguin/python-intmaniac
Author: Axel Bock
Author-email: mr.axel.bock@gmail.com
License: UNKNOWN
Download-URL: https://github.com/flypenguin/python-intmaniac/tarball/0.18.1
Keywords: integrationtest sysadmin devops ci cd
Platform: UNKNOWN
Classifier: License :: OSI Approved :: MIT License
Classifier: Development Status :: 4 - Beta
Classifier: Intended Audience :: Developers
Classifier: Intended Audience :: System Administrators
Classifier: Programming Language :: Python :: 3
Classifier: Operating System :: POSIX
Classifier: Operating System :: MacOS
Classifier: Topic :: System :: Systems Administration
Classifier: Topic :: Software Development :: Testing
Requires-Dist: docker-compose (~=1.10)
Requires-Dist: docker (~=2.0)
Requires-Dist: pyyaml
